{
  "id": "1773525",
  "name": "offical-website",
  "font_family": "iconfont",
  "css_prefix_text": "icon-",
  "description": "",
  "glyphs": [
    {
      "icon_id": "4546968",
      "name": "contact",
      "font_class": "contact",
      "unicode": "e653",
      "unicode_decimal": 58963
    },
    {
      "icon_id": "610147",
      "name": "about",
      "font_class": "about",
      "unicode": "e64a",
      "unicode_decimal": 58954
    },
    {
      "icon_id": "995239",
      "name": "home",
      "font_class": "home",
      "unicode": "e640",
      "unicode_decimal": 58944
    },
    {
      "icon_id": "5275280",
      "name": "projects",
      "font_class": "projects",
      "unicode": "e624",
      "unicode_decimal": 58916
    },
    {
      "icon_id": "12157786",
      "name": "folder",
      "font_class": "folder",
      "unicode": "e604",
      "unicode_decimal": 58884
    },
    {
      "icon_id": "2551875",
      "name": "视频文件",
      "font_class": "video",
      "unicode": "e613",
      "unicode_decimal": 58899
    },
    {
      "icon_id": "2587507",
      "name": "pdf",
      "font_class": "pdf",
      "unicode": "e6ba",
      "unicode_decimal": 59066
    },
    {
      "icon_id": "9371399",
      "name": "PPT",
      "font_class": "ppt",
      "unicode": "e74b",
      "unicode_decimal": 59211
    },
    {
      "icon_id": "9548464",
      "name": "doc",
      "font_class": "doc",
      "unicode": "e603",
      "unicode_decimal": 58883
    },
    {
      "icon_id": "9377423",
      "name": "qr_code",
      "font_class": "qrcode",
      "unicode": "e600",
      "unicode_decimal": 58880
    },
    {
      "icon_id": "10423589",
      "name": "url",
      "font_class": "url",
      "unicode": "e601",
      "unicode_decimal": 58881
    },
    {
      "icon_id": "12365731",
      "name": "Add to download",
      "font_class": "download",
      "unicode": "e602",
      "unicode_decimal": 58882
    },
    {
      "icon_id": "49733",
      "name": "android",
      "font_class": "android",
      "unicode": "e623",
      "unicode_decimal": 58915
    },
    {
      "icon_id": "1031625",
      "name": "ios",
      "font_class": "ios",
      "unicode": "e62a",
      "unicode_decimal": 58922
    },
    {
      "icon_id": "1160269",
      "name": "windows",
      "font_class": "windows",
      "unicode": "e6c9",
      "unicode_decimal": 59081
    },
    {
      "icon_id": "10140048",
      "name": "mobile-phone-2",
      "font_class": "mobile-phone",
      "unicode": "e6aa",
      "unicode_decimal": 59050
    },
    {
      "icon_id": "12843127",
      "name": "website",
      "font_class": "website",
      "unicode": "e861",
      "unicode_decimal": 59489
    }
  ]
}
